mavenworks/MavenWorksServerConf.json
mavenworks/__init__.py
mavenworks/serialization.py
mavenworks/settings.py
mavenworks/dashboard/__init__.py
mavenworks/dashboard/bind.py
mavenworks/dashboard/containers.py
mavenworks/dashboard/dashboard.py
mavenworks/dashboard/helpers.py
mavenworks/dashboard/part.py
mavenworks/parts/DisplayHandle.py
mavenworks/parts/KernelPart.py
mavenworks/parts/PartHelpers.py
mavenworks/parts/PyScatterPart.py
mavenworks/parts/WidgetWrapper.py
mavenworks/parts/__init__.py
mavenworks/parts/interact_wrapper.py
mavenworks/server/__init__.py
mavenworks/server/config_object_tracker.py
mavenworks/server/local_config.py
mavenworks/server/viewer.py
mavenworks/server/static/1.bundle.js
mavenworks/server/static/2.bundle.js
mavenworks/server/static/320c4e08fbbbd271691a.worker.js
mavenworks/server/static/index.html
mavenworks/server/static/main.bundle.js
mavenworks/server/static/viewer.html
mavenworks/services/KernelPartManager.py
mavenworks/services/MetadataComm.py
mavenworks/services/__init__.py
mavenworks/services/expression_evaluator.py
mavenworks-0.0.4.dist-info/LICENSE.md
mavenworks-0.0.4.dist-info/METADATA
mavenworks-0.0.4.dist-info/WHEEL
mavenworks-0.0.4.dist-info/top_level.txt
mavenworks-0.0.4.dist-info/RECORD
