Metadata-Version: 2.1
Name: mavenworks
Version: 0.0.4
Summary: Dashboarding for JupyterLab
Home-page: UNKNOWN
Author: Mavenomics, Inc
License: GPL-3.0 (C) 2019 Mavenomics, Inc.
Platform: UNKNOWN
Classifier: Development Status :: 2 - Pre-Alpha
Classifier: Framework :: IPython
Requires-Python: ~=3.6
Requires-Dist: requests
Requires-Dist: rx (<3,>=1.0)
Requires-Dist: jupyterlab (>1.0)
Requires-Dist: pandas
Requires-Dist: IPython
Requires-Dist: ipywidgets
Requires-Dist: matplotlib
